src/gdrivedl-parallel.py
gdrivedl_parallel-0.1.0.dist-info/METADATA
gdrivedl_parallel-0.1.0.dist-info/WHEEL
gdrivedl_parallel-0.1.0.dist-info/licenses/LICENSE
gdrivedl_parallel-0.1.0.dist-info/RECORD
