Metadata-Version: 2.1
Name: gdrivedl-parallel
Version: 0.1.0
Summary: Python library that allows you to download filers/folders from Google Drive
Project-URL: Homepage, https://github.com/duckduckgrayduck/gdrivedl-parallel
Project-URL: Bug Tracker, https://github.com/duckduckgrayduck/gdrivedl-parallel/issues
Author-email: duckduckgrayduck <sanjin+clouddl@muckrock.com>
License-File: LICENSE
Classifier: License :: OSI Approved :: MIT License
Classifier: Operating System :: OS Independent
Classifier: Programming Language :: Python :: 3
Requires-Python: >=3.7
